adasher/__init__.py
adasher/advanced/__init__.py
adasher/advanced/__util.py
adasher/cards/__card_impl.py
adasher/cards/__init__.py
adasher/data_utils/__init__.py
adasher/data_utils/__util.py
adasher/elements/__init__.py
adasher/elements/impl.py
adasher/elements/styles.py
adasher/elements/util.py
adasher/templates/__init__.py
adasher/templates/__util.py
adasher-0.0.3.dist-info/LICENSE
adasher-0.0.3.dist-info/METADATA
adasher-0.0.3.dist-info/WHEEL
adasher-0.0.3.dist-info/top_level.txt
adasher-0.0.3.dist-info/RECORD
