Metadata-Version: 2.1
Name: adasher
Version: 0.0.3
Summary: Dash with analytics utilities
Home-page: https://github.com/bhanuchander210/adasher.git
Author: Bhanuchander Udhayakumar
Author-email: bhanuchander210@gmail.com
License: MIT
License-File: LICENSE
Requires-Dist: cython (>=0.29.28)
Requires-Dist: python-dateutil (>=2.8.1)
Requires-Dist: dash (>=2.0.0)
Requires-Dist: dash-bootstrap-components (>=1.0.0)
Requires-Dist: pandas (>=1.0.5)
Requires-Dist: mlxtend (>=0.19.0)
